dsmq/__init__.py
dsmq/client.py
dsmq/demo.py
dsmq/example_get_client.py
dsmq/example_put_client.py
dsmq/server.py
dsmq/tests/__init__.py
dsmq/tests/integration_test.py
dsmq/tests/performance_suite.py
dsmq-1.4.1.dist-info/METADATA
dsmq-1.4.1.dist-info/WHEEL
dsmq-1.4.1.dist-info/licenses/LICENSE
dsmq-1.4.1.dist-info/RECORD
