Metadata-Version: 2.4
Name: dsmq
Version: 1.4.1
Summary: A dead simple message queue
License-File: LICENSE
Requires-Python: >=3.10
Requires-Dist: pytest>=8.3.4
Requires-Dist: websockets>=14.1
